wxyz/svg/__init__.py
wxyz/svg/_version.py
wxyz/svg/base.py
wxyz/svg/install.json
wxyz/svg/widget_svg.py
wxyz/svg/js/LICENSE.txt
wxyz/svg/js/README.md
wxyz/svg/js/package.json
wxyz/svg/labextension/package.json
wxyz/svg/labextension/static/333.9b53c2be5c89567a7c0e.js
wxyz/svg/labextension/static/387.aceb60542ddfc8909de5.js
wxyz/svg/labextension/static/519.8922e7c11e483d72a53c.js
wxyz/svg/labextension/static/567.2fe1e83f578b8ef7bdd7.js
wxyz/svg/labextension/static/568.b61915196804ff2ac2f2.js
wxyz/svg/labextension/static/608.95b013e0b3b2c82a0fd4.js
wxyz/svg/labextension/static/657.38093d6b0c54ace86790.js
wxyz/svg/labextension/static/657.38093d6b0c54ace86790.js.LICENSE.txt
wxyz/svg/labextension/static/914.6c043430e674c8a63f04.js
wxyz/svg/labextension/static/remoteEntry.648fc928e05febdacdc2.js
wxyz/svg/labextension/static/style.js
wxyz_svg-0.5.1.data/data/share/jupyter/labextensions/@deathbeds/wxyz-svg/install.json
wxyz_svg-0.5.1.data/data/share/jupyter/labextensions/@deathbeds/wxyz-svg/package.json
wxyz_svg-0.5.1.data/data/share/jupyter/labextensions/@deathbeds/wxyz-svg/static/333.9b53c2be5c89567a7c0e.js
wxyz_svg-0.5.1.data/data/share/jupyter/labextensions/@deathbeds/wxyz-svg/static/387.aceb60542ddfc8909de5.js
wxyz_svg-0.5.1.data/data/share/jupyter/labextensions/@deathbeds/wxyz-svg/static/519.8922e7c11e483d72a53c.js
wxyz_svg-0.5.1.data/data/share/jupyter/labextensions/@deathbeds/wxyz-svg/static/567.2fe1e83f578b8ef7bdd7.js
wxyz_svg-0.5.1.data/data/share/jupyter/labextensions/@deathbeds/wxyz-svg/static/568.b61915196804ff2ac2f2.js
wxyz_svg-0.5.1.data/data/share/jupyter/labextensions/@deathbeds/wxyz-svg/static/608.95b013e0b3b2c82a0fd4.js
wxyz_svg-0.5.1.data/data/share/jupyter/labextensions/@deathbeds/wxyz-svg/static/657.38093d6b0c54ace86790.js
wxyz_svg-0.5.1.data/data/share/jupyter/labextensions/@deathbeds/wxyz-svg/static/657.38093d6b0c54ace86790.js.LICENSE.txt
wxyz_svg-0.5.1.data/data/share/jupyter/labextensions/@deathbeds/wxyz-svg/static/914.6c043430e674c8a63f04.js
wxyz_svg-0.5.1.dist-info/LICENSE.txt
wxyz_svg-0.5.1.dist-info/METADATA
wxyz_svg-0.5.1.dist-info/WHEEL
wxyz_svg-0.5.1.dist-info/top_level.txt
wxyz_svg-0.5.1.dist-info/RECORD
